<?xml version="1.0" encoding="UTF-8"?>
<gresources>
  <gresource prefix="/io/github/superuser_miguel/Vitrine">
    <file compressed="true">window.ui</file>
    <file compressed="true">grid_cell.ui</file>
    <file compressed="true">viewer.ui</file>
    <file compressed="true">style.css</file>
    <!-- App-bundled symbolic icons (registered on the default IconTheme in
         main.rs); GTK recolors them like any theme icon. -->
    <file compressed="true" alias="icons/scalable/actions/tag-symbolic.svg">icons/hicolor/scalable/actions/tag-symbolic.svg</file>
  </gresource>
</gresources>
